[
  {
    "ContainingType": "StudentManagementAPI.Controllers.StudentController",
    "Method": "GetStudentNames",
    "RelativePath": "api/Student/GiveMeAllStudents",
    "HttpMethod": "GET",
    "IsController": true,
    "Order": 0,
    "Parameters": [],
    "ReturnTypes": [
      {
        "Type": "System.Collections.Generic.List\u00601[[Common.Models.Student, Common, Version=1.0.0.0, Culture=neutral, PublicKeyToken=null]]",
        "MediaTypes": [
          "text/plain",
          "application/json",
          "text/json"
        ],
        "StatusCode": 200
      }
    ]
  }
]